bashckup/__init__.py
bashckup/bashckup.py
bashckup/actuators/__init__.py
bashckup/actuators/actuators.py
bashckup/actuators/actuators_factories.py
bashckup/actuators/exceptions.py
bashckup/actuators/post_backup.py
bashckup/actuators/readers.py
bashckup/actuators/transformers.py
bashckup/actuators/writers.py
bashckup-0.1.1.dist-info/METADATA
bashckup-0.1.1.dist-info/WHEEL
bashckup-0.1.1.dist-info/entry_points.txt
bashckup-0.1.1.dist-info/licenses/LICENSE
bashckup-0.1.1.dist-info/RECORD
