Metadata-Version: 2.1
Name: bashckup
Version: 0.1.1
Summary: Defines your backup strategy based on bash commands
Project-URL: Homepage, https://github.com/remi-angenieux/bashckup
Project-URL: Bug Tracker, https://github.com/remi-angenieux/bashckup/issues
Author: Rémi Angénieux
License: MIT License
License-File: LICENSE
Classifier: Development Status :: 3 - Alpha
Classifier: License :: OSI Approved :: MIT License
Classifier: Operating System :: Unix
Classifier: Programming Language :: Python :: 3.7
Classifier: Programming Language :: Python :: 3.8
Classifier: Programming Language :: Python :: 3.9
Classifier: Programming Language :: Python :: 3.10
Classifier: Topic :: System :: Archiving :: Backup
Requires-Python: >=3.7
Requires-Dist: jsonschema
Requires-Dist: pyyaml
Provides-Extra: tests
Requires-Dist: assertpy; extra == 'tests'
Requires-Dist: freezegun; extra == 'tests'
Requires-Dist: pytest; extra == 'tests'
Requires-Dist: pytest-cov; extra == 'tests'
